CtfAllInOne20171015/README.md
CtfAllInOne20171015/__init__.py
CtfAllInOne20171015/__main__.py
CtfAllInOne20171015/file.epub
CtfAllInOne20171015/index.html
CtfAllInOne20171015/css/__init__.py
CtfAllInOne20171015/css/annotations.css
CtfAllInOne20171015/css/main.css
CtfAllInOne20171015/css/normalize.css
CtfAllInOne20171015/css/popup.css
CtfAllInOne20171015/font/__init__.py
CtfAllInOne20171015/font/fontello.eot
CtfAllInOne20171015/font/fontello.svg
CtfAllInOne20171015/font/fontello.ttf
CtfAllInOne20171015/font/fontello.woff
CtfAllInOne20171015/img/__init__.py
CtfAllInOne20171015/img/annotator-glyph-sprite.png
CtfAllInOne20171015/img/annotator-icon-sprite.png
CtfAllInOne20171015/img/apple-touch-icon.png
CtfAllInOne20171015/img/cancelfullscreen.png
CtfAllInOne20171015/img/close.png
CtfAllInOne20171015/img/fullscreen.png
CtfAllInOne20171015/img/loader.gif
CtfAllInOne20171015/img/menu-icon.png
CtfAllInOne20171015/img/save.png
CtfAllInOne20171015/img/saved.png
CtfAllInOne20171015/img/settings-s.png
CtfAllInOne20171015/img/settings.png
CtfAllInOne20171015/img/star.png
CtfAllInOne20171015/js/__init__.py
CtfAllInOne20171015/js/epub.js
CtfAllInOne20171015/js/epub.min.js
CtfAllInOne20171015/js/epub.min.map
CtfAllInOne20171015/js/hooks.min.js
CtfAllInOne20171015/js/hooks.min.map
CtfAllInOne20171015/js/reader.js
CtfAllInOne20171015/js/reader.js.map
CtfAllInOne20171015/js/reader.min.js
CtfAllInOne20171015/js/reader.min.map
CtfAllInOne20171015/js/hooks/__init__.py
CtfAllInOne20171015/js/hooks/extensions/__init__.py
CtfAllInOne20171015/js/hooks/extensions/highlight.js
CtfAllInOne20171015/js/libs/__init__.py
CtfAllInOne20171015/js/libs/jquery.min.js
CtfAllInOne20171015/js/libs/localforage.min.js
CtfAllInOne20171015/js/libs/screenfull.js
CtfAllInOne20171015/js/libs/screenfull.min.js
CtfAllInOne20171015/js/libs/zip.min.js
CtfAllInOne20171015/js/plugins/__init__.py
CtfAllInOne20171015/js/plugins/hypothesis.js
CtfAllInOne20171015/js/plugins/search.js
ctf_all_in_one_20171015-2024.3.2.0.dist-info/METADATA
ctf_all_in_one_20171015-2024.3.2.0.dist-info/WHEEL
ctf_all_in_one_20171015-2024.3.2.0.dist-info/entry_points.txt
ctf_all_in_one_20171015-2024.3.2.0.dist-info/top_level.txt
ctf_all_in_one_20171015-2024.3.2.0.dist-info/RECORD
